[
    {
        "name": "Product 1",
        "category": "body",
        "price": 9.24,
        "image": "/images/1.jpg"
    },
    {
        "name": "Product 2",
        "category": "face",
        "price": 5.25,
        "image": "/images/2.jpg"
    },
    {
        "name": "Product 3",
        "category": "face",
        "price": 4,
        "image": "/images/3.jpg"
    },
    {
        "name": "Product 4",
        "category": "hair",
        "price": 3.8,
        "image": "/images/4.jpg"
    },
    {
        "name": "Product 5",
        "category": "body",
        "price": 1.9,
        "image": "/images/5.jpg"
    },
    {
        "name": "Product 6",
        "category": "hair",
        "price": 2.2,
        "image": "/images/6.jpg"
    },
    {
        "name": "Product 8",
        "category": "face",
        "price": 8.2,
        "image": "/images/8.jpg",
    },
    {
        "name": "Product 9",
        "category": "body",
        "price": 9.5,
        "image": "/images/9.jpg",
    },
    {
        "name": "Product 10",
        "category": "hair",
        "price": 10.85,
        "image": "/images/10.jpg",
    },
    {
        "name": "Product 11",
        "category": "face",
        "price": 11.29,
        "image": "/images/11.jpg"
    }
    
    
]